sqlalchemy_pglogical/__init__.py
sqlalchemy_pglogical/base.py
sqlalchemy_pglogical/replicate_alembic.py
sqlalchemy_pglogical/replicate_ddl.py
sqlalchemy_pglogical-0.1.0.dist-info/LICENSE.md
sqlalchemy_pglogical-0.1.0.dist-info/METADATA
sqlalchemy_pglogical-0.1.0.dist-info/WHEEL
sqlalchemy_pglogical-0.1.0.dist-info/RECORD
