Metadata-Version: 2.1
Name: sqlalchemy-pglogical
Version: 0.1.0
Summary: 
Home-page: https://github.com/brandfolder/sqlalchemy-pglogical
License: MIT
Keywords: pglogical,postgres,sqlalchemy,alembic
Author: Ben Berry
Author-email: benjamin.berry@smartsheet.com
Requires-Python: >=3.8,<=3.12
Classifier: Development Status :: 4 - Beta
Classifier: Environment :: Console
Classifier: Intended Audience :: Developers
Classifier: License :: OSI Approved :: MIT License
Classifier: Programming Language :: Python :: 3
Classifier: Programming Language :: Python :: 3.8
Classifier: Programming Language :: Python :: 3.9
Classifier: Programming Language :: Python :: 3.10
Classifier: Programming Language :: Python :: 3.11
Classifier: Programming Language :: Python :: 3.12
Classifier: Topic :: Database :: Front-Ends
Requires-Dist: alembic (>=1.7.0,<2.0.0)
Requires-Dist: sqlalchemy (>=1.4,<=2)
Project-URL: Bug Tracker, https://github.com/brandfolder/sqlalchemy-pglogical/issues
Project-URL: Documentation, https://github.com/brandfolder/sqlalchemy-pglogical/blob/main/README.md
Project-URL: Repository, https://github.com/brandfolder/sqlalchemy-pglogical
Project-URL: changelog, https://github.com/brandfolder/sqlalchemy-pglogical/blob/main/CHANGELOG.md
